mcsmp/__init__.py
mcsmp/client.py
mcsmp/endpoints/__init__.py
mcsmp/endpoints/allow_list.py
mcsmp/endpoints/bans.py
mcsmp/endpoints/gamerules.py
mcsmp/endpoints/ip_bans.py
mcsmp/endpoints/operators.py
mcsmp/endpoints/players.py
mcsmp/endpoints/server.py
mcsmp/endpoints/server_settings.py
mcsmp/jsonrpc/__init__.py
mcsmp/jsonrpc/error.py
mcsmp/jsonrpc/error_code.py
mcsmp/jsonrpc/request.py
mcsmp/jsonrpc/response.py
mcsmp/schemas/__init__.py
mcsmp/schemas/difficulty.py
mcsmp/schemas/game_type.py
mcsmp/schemas/incoming_ip_ban.py
mcsmp/schemas/ip_ban.py
mcsmp/schemas/kick_player.py
mcsmp/schemas/message.py
mcsmp/schemas/operator.py
mcsmp/schemas/player.py
mcsmp/schemas/server_state.py
mcsmp/schemas/system_message.py
mcsmp/schemas/typed_game_rule.py
mcsmp/schemas/untyped_game_rule.py
mcsmp/schemas/user_ban.py
mcsmp/schemas/version.py
mcsmp-0.0.1.dist-info/METADATA
mcsmp-0.0.1.dist-info/WHEEL
mcsmp-0.0.1.dist-info/licenses/LICENSE
mcsmp-0.0.1.dist-info/RECORD
