Metadata-Version: 2.4
Name: mcsmp
Version: 0.0.1
Summary: A client library for interacting with the Minecraft Server Management Protocol.
Project-URL: Homepage, https://github.com/TechnoBro03/MC-SMP
Project-URL: Issues, https://github.com/TechnoBro03/MC-SMP/issues
Project-URL: Wiki, https://github.com/TechnoBro03/MC-SMP/wiki
Author: TechnoBro03
License-Expression: MIT
License-File: LICENSE
Classifier: Operating System :: OS Independent
Classifier: Programming Language :: Python :: 3
Classifier: Programming Language :: Python :: 3.10
Classifier: Typing :: Typed
Requires-Python: >=3.10
Requires-Dist: pydantic
Requires-Dist: pyeventic
Requires-Dist: websockets
Provides-Extra: test
Requires-Dist: mypy; extra == 'test'
